verisure/__init__.py
verisure/__main__.py
verisure/session.py
verisure/urls.py
vsure-1.7.0.dist-info/LICENSE
vsure-1.7.0.dist-info/METADATA
vsure-1.7.0.dist-info/WHEEL
vsure-1.7.0.dist-info/entry_points.txt
vsure-1.7.0.dist-info/top_level.txt
vsure-1.7.0.dist-info/zip-safe
vsure-1.7.0.dist-info/RECORD
