Metadata-Version: 2.1
Name: vsure
Version: 1.7.0
Summary: Read and change status of verisure devices through mypages.
Home-page: http://github.com/persandstrom/python-verisure
Author: Per Sandstrom
Author-email: per.j.sandstrom@gmail.com
License: MIT
Keywords: home automation verisure
Platform: UNKNOWN
Classifier: Development Status :: 4 - Beta
Classifier: Intended Audience :: Developers
Classifier: Topic :: Home Automation
Classifier: License :: OSI Approved :: MIT License
Classifier: Programming Language :: Python :: 2
Classifier: Programming Language :: Python :: 2.6
Classifier: Programming Language :: Python :: 2.7
Classifier: Programming Language :: Python :: 3
Classifier: Programming Language :: Python :: 3.4
Classifier: Programming Language :: Python :: 3.5
Requires-Dist: requests (>=2.20.0)
